cardroom/__init__.py
cardroom/py.typed
cardroom/table.py
cardroom/utilities.py
cardroom/tests/__init__.py
cardroom/tests/test_table.py
cardroom/tests/test_utilities.py
cardroom-0.0.0.dist-info/LICENSE
cardroom-0.0.0.dist-info/METADATA
cardroom-0.0.0.dist-info/WHEEL
cardroom-0.0.0.dist-info/top_level.txt
cardroom-0.0.0.dist-info/RECORD
