Metadata-Version: 2.1
Name: cardroom
Version: 0.0.0
Summary: Poker tournament and table management library
Home-page: https://github.com/uoftcprg/cardroom
Author: University of Toronto Computer Poker Research Group
Author-email: uoftcprg@outlook.com
License: MIT
Project-URL: Documentation, https://cardroom.readthedocs.io/en/latest/
Project-URL: Source, https://github.com/uoftcprg/cardroom
Project-URL: Tracker, https://github.com/uoftcprg/cardroom/issues
Keywords: game,game-development,holdem-poker,imperfect-information-game,poker,poker-engine,poker-game,poker-library,poker-strategies,python,texas-holdem
Classifier: Development Status :: 5 - Production/Stable
Classifier: Intended Audience :: Developers
Classifier: Intended Audience :: Education
Classifier: Topic :: Education
Classifier: Topic :: Games/Entertainment
Classifier: Topic :: Games/Entertainment :: Board Games
Classifier: Topic :: Scientific/Engineering
Classifier: Topic :: Scientific/Engineering :: Artificial Intelligence
Classifier: License :: OSI Approved :: MIT License
Classifier: Operating System :: OS Independent
Classifier: Programming Language :: Python
Classifier: Programming Language :: Python :: 3
Classifier: Programming Language :: Python :: 3 :: Only
Classifier: Programming Language :: Python :: 3.11
Classifier: Programming Language :: Python :: 3.12
Requires-Python: >=3.11
License-File: LICENSE
Requires-Dist: pokerkit ~=0.3.0
